{
    "AssignedPrivileges@odata.count": 5,
    "Description": "Administrator User Role",
    "@odata.context": "/redfish/v1/$metadata#Role.Role",
    "AssignedPrivileges": [
        "Login",
        "ConfigureManager",
        "ConfigureUser",
        "ConfigureComponent",
        "ConfigureSelf"
    ],
    "IsPredefined": true,
    "@odata.type": "#Role.v1_0_2.Role",
    "Id": "Administrator",
    "Name": "User Role",
    "@Redfish.Copyright": "Copyright 2017 Dell Inc. All rights reserved.",
    "@odata.id": "/redfish/v1/Managers/iDRAC.Embedded.1/Roles/Administrator"
}