{
    "Location": [
        {
            "Language": "en",
            "Uri": "/redfish/v1/Schemas/IPAddresses.v1_0_2.json",
            "PublicationUri": "http://redfish.dmtf.org/schemas/v1/IPAddresses.v1_0_2.json"
        }
    ],
    "@odata.id": "/redfish/v1/JSONSchemas/IPAddresses.v1_0_2",
    "Id": "IPAddresses.v1_0_2",
    "Languages": [
        "en"
    ],
    "@odata.context": "/redfish/v1/$metadata#JsonSchemaFile.JsonSchemaFile",
    "@Redfish.Copyright": "Copyright 2017 Dell Inc. All rights reserved.",
    "Languages@odata.count": 1,
    "Description": "IPAddresses Schema File Location",
    "Schema": "#IPAddresses.v1_0_2.IPAddresses",
    "Name": "IPAddresses Schema File",
    "Location@odata.count": 1,
    "@odata.type": "#JsonSchemaFile.v1_0_2.JsonSchemaFile"
}