{
    "Location": [
        {
            "Language": "en",
            "Uri": "/redfish/v1/Schemas/LogEntry.v1_0_2.json",
            "PublicationUri": "http://redfish.dmtf.org/schemas/v1/LogEntry.v1_0_2.json"
        }
    ],
    "@odata.id": "/redfish/v1/JSONSchemas/LogEntry.v1_0_2",
    "Id": "LogEntry.v1_0_2",
    "Languages": [
        "en"
    ],
    "@odata.context": "/redfish/v1/$metadata#JsonSchemaFile.JsonSchemaFile",
    "@Redfish.Copyright": "Copyright 2017 Dell Inc. All rights reserved.",
    "Languages@odata.count": 1,
    "Description": "LogEntry Schema File Location",
    "Schema": "#LogEntry.v1_0_2.LogEntry",
    "Name": "LogEntry Schema File",
    "Location@odata.count": 1,
    "@odata.type": "#JsonSchemaFile.v1_0_2.JsonSchemaFile"
}